inlayr/__init__.py
inlayr/py.typed
inlayr/aggregators/__init__.py
inlayr/aggregators/jupiter.py
inlayr/aggregators/oneinch.py
inlayr/aggregators/raydium.py
inlayr/aggregators/zeroex.py
inlayr/chains/__init__.py
inlayr/chains/evm.py
inlayr/chains/solana.py
inlayr/domain/__init__.py
inlayr/domain/errors.py
inlayr/domain/models.py
inlayr/provider/__init__.py
inlayr/provider/provider.py
inlayr/provider/registry.py
inlayr/rpcs/__init__.py
inlayr/rpcs/ankr.py
inlayr/rpcs/onerpc.py
inlayr/rpcs/solana.py
inlayr/utils/__init__.py
inlayr/utils/constants.py
inlayr/utils/defaults.yaml
inlayr/utils/http.py
inlayr/utils/validation.py
inlayr-0.2.1.dist-info/licenses/LICENSE
inlayr-0.2.1.dist-info/METADATA
inlayr-0.2.1.dist-info/WHEEL
inlayr-0.2.1.dist-info/top_level.txt
inlayr-0.2.1.dist-info/RECORD
