Metadata-Version: 2.4
Name: inlayr
Version: 0.2.1
Summary: Modular, chain-agnostic SDK for crypto trading on DEXs
Author: Oleg Mitsik
License-Expression: Apache-2.0
Project-URL: Homepage, https://github.com/OlegMitsik/inlayr
Project-URL: Repository, https://github.com/OlegMitsik/inlayr
Project-URL: Issues, https://github.com/OlegMitsik/inlayr/issues
Keywords: blockchain,defi,aggregator,solana,ethereum
Classifier: Programming Language :: Python
Classifier: Programming Language :: Python :: 3
Classifier: Intended Audience :: Developers
Classifier: Topic :: Software Development :: Libraries
Classifier: Typing :: Typed
Requires-Python: >=3.9
License-File: LICENSE
Requires-Dist: requests
Requires-Dist: frozendict
Requires-Dist: PyYAML
Requires-Dist: urllib3
Provides-Extra: test
Requires-Dist: pytest; extra == "test"
Requires-Dist: pytest-cov; extra == "test"
Provides-Extra: solana
Requires-Dist: spl; extra == "solana"
Requires-Dist: solana; extra == "solana"
Requires-Dist: solders; extra == "solana"
Provides-Extra: evm
Requires-Dist: web3; extra == "evm"
Requires-Dist: eth_account; extra == "evm"
Dynamic: license-file
